PythonFunctions/Board.py
PythonFunctions/Check.py
PythonFunctions/CleanFolderData.py
PythonFunctions/Colours.py
PythonFunctions/Convert.py
PythonFunctions/Encryption.py
PythonFunctions/IsDigit.py
PythonFunctions/Message.py
PythonFunctions/PrintTraceback.py
PythonFunctions/Run.py
PythonFunctions/Save.py
PythonFunctions/Searching.py
PythonFunctions/TerminalDisplay.py
PythonFunctions/Version.py
PythonFunctions/Watermark.py
PythonFunctions/__init__.py
PythonFunctions/__main__.py
PythonFunctions/ui.py
PythonFunctions/Checks/INT.py
PythonFunctions/Checks/__init__.py
PythonFunctions/Checks/path.py
PythonFunctions/Checks/str.py
PythonFunctions/Checks/yn.py
PythonFunctions/SaveModules/FTP.py
PythonFunctions/SaveModules/GOOGLE.py
PythonFunctions/SaveModules/NORMAL.py
PythonFunctions/SaveModules/OTHER.py
PythonFunctions/SaveModules/__init__.py
PythonFunctions/SaveModules/template.py
PythonFunctions-1.4.15.dist-info/LICENCE
PythonFunctions-1.4.15.dist-info/METADATA
PythonFunctions-1.4.15.dist-info/WHEEL
PythonFunctions-1.4.15.dist-info/top_level.txt
PythonFunctions-1.4.15.dist-info/RECORD
