Metadata-Version: 2.1
Name: PythonFunctions
Version: 1.4.15
Summary: A list of functions ready to install and use.
Author: Dragmine149
Project-URL: Homepage, https://github.com/FunAndHelpfulDragon/python-Functions/
Project-URL: Bug Tracker, https://github.com/FunAndHelpfulDragon/python-Functions/issues
Classifier: Programming Language :: Python :: 3
Classifier: License :: OSI Approved :: MIT License
Classifier: Operating System :: OS Independent
Requires-Python: >=3.7
License-File: LICENCE
Requires-Dist: colorama
Requires-Dist: requests
Requires-Dist: packaging
Provides-Extra: all
Requires-Dist: moviepy (>1.0.0) ; extra == 'all'
Requires-Dist: google-api-python-client ; extra == 'all'
Requires-Dist: google-auth-httplib2 ; extra == 'all'
Requires-Dist: google-auth-oauthlib ; extra == 'all'
Requires-Dist: pytest (>=7.2.0) ; extra == 'all'
Requires-Dist: pytest-repeat (>=0.9.1) ; extra == 'all'
Requires-Dist: pylint (>=2.15.5) ; extra == 'all'
Requires-Dist: cryptography (>=38.0.3) ; extra == 'all'
Requires-Dist: readchar ; extra == 'all'
Provides-Extra: audio
Requires-Dist: moviepy (>1.0.0) ; extra == 'audio'
Provides-Extra: encryption
Requires-Dist: cryptography (>=38.0.3) ; extra == 'encryption'
Provides-Extra: google
Requires-Dist: google-api-python-client ; extra == 'google'
Requires-Dist: google-auth-httplib2 ; extra == 'google'
Requires-Dist: google-auth-oauthlib ; extra == 'google'
Provides-Extra: terminal
Requires-Dist: readchar ; extra == 'terminal'
Provides-Extra: tools
Requires-Dist: pytest (>=7.2.0) ; extra == 'tools'
Requires-Dist: pytest-repeat (>=0.9.1) ; extra == 'tools'
Requires-Dist: pylint (>=2.15.5) ; extra == 'tools'
